{
  "NSP_INSTALL": [
    "Удалять после установки: "
  ],
  "SETTINGS": [],
  "FW_INFO": [
    "Сожжено предохранителей : {}"
  ],
  "AMS_INFO": [
    "Форсировано вклчение USB 3.0: {}"
  ],
  "SD_INFO": [
    "Ревизия продукта : {:s}"
  ],
  "POWER_INFO": [
    "Заряд батареи (сырое значение) : {}",
    "Заряд батареи (сырое значение) : {}%",
    "Возраст батареи                 : {}%",
    "Возраст батареи                : {}",
    "Возраст батареи                : {}%"
  ],
  "CHARGE_INFO": [
    "Предел напряжения заряда батареи: {} mV",
    "Возраст батареи                 : {}%",
    "Возраст батареи                : {}",
    "Возраст батареи                : {}%"
  ],
  "BATTERY_CONTROLLER_INFO": [
    "Сумма %% заряд-разряд: {} (~{} 0-100 циклов)"
  ],
  "MAX17050_INFO": [
    "Средняя температура: {}°C"
  ],
  "HW_INFO": [
    "Wireless LAN MAC адрес: {:02X}:{:02X}:{:02X}:{:02X}:{:02X}:{:02X}"
  ],
  "ACTIVITY_INFO": [
    "RTC запущены (приблизительно) : {}",
    "Дата первого игрового события : {}"
  ]
}